{"success": true, "data": [{"requirements": null, "name": "Hint 297", "type": "standard", "category": "hints", "icon": null, "id": 3605, "user_id": 207, "user": 207, "date": "2025-09-21T21:00:30.025886+00:00", "value": 0, "team": 134, "description": "Hint for I. The Pledge", "team_id": 134}, {"requirements": null, "name": "Hint 296", "type": "standard", "category": "hints", "icon": null, "id": 3603, "user_id": 207, "user": 207, "date": "2025-09-21T21:00:27.255160+00:00", "value": 0, "team": 134, "description": "Hint for I. The Pledge", "team_id": 134}, {"requirements": null, "name": "Hint 295", "type": "standard", "category": "hints", "icon": null, "id": 3602, "user_id": 207, "user": 207, "date": "2025-09-21T21:00:22.521701+00:00", "value": 0, "team": 134, "description": "Hint for I. The Pledge", "team_id": 134}, {"requirements": null, "name": "Hint 347", "type": "standard", "category": "hints", "icon": null, "id": 3574, "user_id": 207, "user": 207, "date": "2025-09-21T20:56:14.680227+00:00", "value": 0, "team": 134, "description": "Hint for Magic 103", "team_id": 134}, {"requirements": null, "name": "Hint 346", "type": "standard", "category": "hints", "icon": null, "id": 3572, "user_id": 207, "user": 207, "date": "2025-09-21T20:56:11.043763+00:00", "value": 0, "team": 134, "description": "Hint for Magic 103", "team_id": 134}, {"requirements": null, "name": "Hint 345", "type": "standard", "category": "hints", "icon": null, "id": 3571, "user_id": 207, "user": 207, "date": "2025-09-21T20:56:08.018311+00:00", "value": 0, "team": 134, "description": "Hint for Magic 103", "team_id": 134}, {"requirements": null, "name": "Hint 290", "type": "standard", "category": "hints", "icon": null, "id": 3535, "user_id": 207, "user": 207, "date": "2025-09-21T20:51:48.379800+00:00", "value": 0, "team": 134, "description": "Hint for Magic 102", "team_id": 134}, {"requirements": null, "name": "Hint 289", "type": "standard", "category": "hints", "icon": null, "id": 3533, "user_id": 207, "user": 207, "date": "2025-09-21T20:51:45.457151+00:00", "value": 0, "team": 134, "description": "Hint for Magic 102", "team_id": 134}, {"requirements": null, "name": "Hint 288", "type": "standard", "category": "hints", "icon": null, "id": 3530, "user_id": 207, "user": 207, "date": "2025-09-21T20:51:42.208273+00:00", "value": 0, "team": 134, "description": "Hint for Magic 102", "team_id": 134}, {"requirements": null, "name": "Hint 294", "type": "standard", "category": "hints", "icon": null, "id": 3496, "user_id": 207, "user": 207, "date": "2025-09-21T20:47:50.515891+00:00", "value": 0, "team": 134, "description": "Hint for pwntools", "team_id": 134}, {"requirements": null, "name": "Hint 333", "type": "standard", "category": "hints", "icon": null, "id": 3356, "user_id": 207, "user": 207, "date": "2025-09-21T20:34:22.852630+00:00", "value": 0, "team": 134, "description": "Hint for CS404 MP0", "team_id": 134}, {"requirements": null, "name": "Hint 273", "type": "standard", "category": "hints", "icon": null, "id": 3352, "user_id": 207, "user": 207, "date": "2025-09-21T20:33:10.669468+00:00", "value": 0, "team": 134, "description": "Hint for grep -R /cif fallctf", "team_id": 134}, {"requirements": null, "name": "Hint 341", "type": "standard", "category": "hints", "icon": null, "id": 3256, "user_id": 207, "user": 207, "date": "2025-09-21T20:23:17.364366+00:00", "value": 0, "team": 134, "description": "Hint for Champaign Problems 5", "team_id": 134}, {"requirements": null, "name": "Hint 286", "type": "standard", "category": "hints", "icon": null, "id": 3124, "user_id": 207, "user": 207, "date": "2025-09-21T20:10:10.879284+00:00", "value": 0, "team": 134, "description": "Hint for Schengen Shuffle I", "team_id": 134}, {"requirements": null, "name": "Hint 342", "type": "standard", "category": "hints", "icon": null, "id": 2898, "user_id": 207, "user": 207, "date": "2025-09-21T19:51:44.138393+00:00", "value": 0, "team": 134, "description": "Hint for Champaign Problems 4", "team_id": 134}, {"requirements": null, "name": "Hint 344", "type": "standard", "category": "hints", "icon": null, "id": 2864, "user_id": 207, "user": 207, "date": "2025-09-21T19:49:13.146839+00:00", "value": 0, "team": 134, "description": "Hint for Champaign Problems 3", "team_id": 134}, {"requirements": null, "name": "Hint 275", "type": "standard", "category": "hints", "icon": null, "id": 2747, "user_id": 207, "user": 207, "date": "2025-09-21T19:37:07.015047+00:00", "value": 0, "team": 134, "description": "Hint for I'm Blue 1", "team_id": 134}, {"requirements": null, "name": "Hint 274", "type": "standard", "category": "hints", "icon": null, "id": 2746, "user_id": 207, "user": 207, "date": "2025-09-21T19:37:04.243700+00:00", "value": 0, "team": 134, "description": "Hint for I'm Blue 1", "team_id": 134}, {"requirements": null, "name": "Hint 276", "type": "standard", "category": "hints", "icon": null, "id": 2740, "user_id": 207, "user": 207, "date": "2025-09-21T19:36:43.028676+00:00", "value": 0, "team": 134, "description": "Hint for I'm Blue 2", "team_id": 134}, {"requirements": null, "name": "Hint 343", "type": "standard", "category": "hints", "icon": null, "id": 2728, "user_id": 207, "user": 207, "date": "2025-09-21T19:35:31.365702+00:00", "value": 0, "team": 134, "description": "Hint for Champaign Problems 2", "team_id": 134}, {"requirements": null, "name": "Hint 340", "type": "standard", "category": "hints", "icon": null, "id": 2714, "user_id": 207, "user": 207, "date": "2025-09-21T19:34:07.350676+00:00", "value": 0, "team": 134, "description": "Hint for Champaign Problems 1", "team_id": 134}, {"requirements": null, "name": "Hint 326", "type": "standard", "category": "hints", "icon": null, "id": 2482, "user_id": 207, "user": 207, "date": "2025-09-21T19:18:55.449395+00:00", "value": 0, "team": 134, "description": "Hint for Inspect Away 10", "team_id": 134}, {"requirements": null, "name": "Hint 327", "type": "standard", "category": "hints", "icon": null, "id": 2479, "user_id": 207, "user": 207, "date": "2025-09-21T19:18:05.002863+00:00", "value": 0, "team": 134, "description": "Hint for Inspect Away 6", "team_id": 134}], "meta": {"count": 23}}
