{"success": true, "data": [{"name": "Hint 304", "category": "hints", "icon": null, "date": "2025-09-21T20:24:33.578681+00:00", "user_id": 148, "user": 148, "id": 3273, "value": 0, "team": 93, "description": "Hint for Flag Generator", "team_id": 93}, {"name": "Hint 303", "category": "hints", "icon": null, "date": "2025-09-21T20:24:31.143991+00:00", "user_id": 148, "user": 148, "id": 3272, "value": 0, "team": 93, "description": "Hint for Flag Generator", "team_id": 93}, {"name": "Hint 265", "category": "hints", "icon": null, "date": "2025-09-21T19:59:39.744662+00:00", "user_id": 148, "user": 148, "id": 3008, "value": 0, "team": 93, "description": "Hint for First Rule of Security", "team_id": 93}, {"name": "Hint 340", "category": "hints", "icon": null, "date": "2025-09-21T19:52:56.923550+00:00", "user_id": 148, "user": 148, "id": 2922, "value": 0, "team": 93, "description": "Hint for Champaign Problems 1", "team_id": 93}, {"name": "Hint 294", "category": "hints", "icon": null, "date": "2025-09-21T18:53:53.717971+00:00", "user_id": 148, "user": 148, "id": 2057, "value": 0, "team": 93, "description": "Hint for pwntools", "team_id": 93}, {"name": "Hint 287", "category": "hints", "icon": null, "date": "2025-09-21T18:45:12.199729+00:00", "user_id": 148, "user": 148, "id": 1874, "value": 0, "team": 93, "description": "Hint for Magic 101", "team_id": 93}, {"name": "Hint 353", "category": "hints", "icon": null, "date": "2025-09-21T18:43:56.443970+00:00", "user_id": 148, "user": 148, "id": 1837, "value": 0, "team": 93, "description": "Hint for FTX Feedback 2", "team_id": 93}, {"name": "Hint 352", "category": "hints", "icon": null, "date": "2025-09-21T18:43:44.756702+00:00", "user_id": 148, "user": 148, "id": 1832, "value": 0, "team": 93, "description": "Hint for FTX Feedback 2", "team_id": 93}, {"name": "Hint 326", "category": "hints", "icon": null, "date": "2025-09-21T18:25:03.863462+00:00", "user_id": 148, "user": 148, "id": 1455, "value": 0, "team": 93, "description": "Hint for Inspect Away 10", "team_id": 93}, {"name": "Hint 320", "category": "hints", "icon": null, "date": "2025-09-21T17:32:44.881693+00:00", "user_id": 148, "user": 148, "id": 390, "value": 0, "team": 93, "description": "Hint for FTX Feedback 1", "team_id": 93}], "meta": {"count": 10}}
