{"success": true, "data": [{"challenge": {"name": "Ask For Help 2", "value": 250, "category": "Welcome", "id": 39}, "team": {"name": "jroja", "id": 51}, "type": "correct", "challenge_id": 39, "id": 9385, "date": "2025-09-21T22:28:06.101659+00:00", "user": {"name": "sriram", "id": 92}}, {"challenge": {"name": "Boot Flag", "value": 462, "category": "Badge", "id": 37}, "team": {"name": "jroja", "id": 51}, "type": "correct", "challenge_id": 37, "id": 7913, "date": "2025-09-21T20:47:44.654382+00:00", "user": {"name": "sriram", "id": 92}}, {"challenge": {"name": "REDLattice", "value": 300, "category": "Welcome", "id": 41}, "team": {"name": "jroja", "id": 51}, "type": "correct", "challenge_id": 41, "id": 7899, "date": "2025-09-21T20:45:58.272266+00:00", "user": {"name": "sriram", "id": 92}}, {"challenge": {"name": "Checkout our Shirt!", "value": 361, "category": "Misc", "id": 46}, "team": {"name": "jroja", "id": 51}, "type": "correct", "challenge_id": 46, "id": 7257, "date": "2025-09-21T20:10:30.603196+00:00", "user": {"name": "rojas80", "id": 80}}, {"challenge": {"name": "String Theory", "value": 244, "category": "Forensics", "id": 3}, "team": {"name": "jroja", "id": 51}, "type": "correct", "challenge_id": 3, "id": 6669, "date": "2025-09-21T19:43:18.995673+00:00", "user": {"name": "sriram", "id": 92}}, {"challenge": {"name": "Call the eXORcist", "value": 352, "category": "Crypto", "id": 1}, "team": {"name": "jroja", "id": 51}, "type": "correct", "challenge_id": 1, "id": 6189, "date": "2025-09-21T19:25:08.443655+00:00", "user": {"name": "sriram", "id": 92}}, {"challenge": {"name": "Inspect Away 8", "value": 269, "category": "Web", "id": 26}, "team": {"name": "jroja", "id": 51}, "type": "correct", "challenge_id": 26, "id": 6020, "date": "2025-09-21T19:17:08.092418+00:00", "user": {"name": "rojas80", "id": 80}}, {"challenge": {"name": "Inspect Away 5", "value": 293, "category": "Web", "id": 23}, "team": {"name": "jroja", "id": 51}, "type": "correct", "challenge_id": 23, "id": 5761, "date": "2025-09-21T19:06:41.313977+00:00", "user": {"name": "rojas80", "id": 80}}, {"challenge": {"name": "Champaign Problems 5", "value": 281, "category": "OSINT", "id": 63}, "team": {"name": "jroja", "id": 51}, "type": "correct", "challenge_id": 63, "id": 4485, "date": "2025-09-21T18:31:59.338049+00:00", "user": {"name": "rojas80", "id": 80}}, {"challenge": {"name": "Instructions Sold Separately", "value": 326, "category": "Rev", "id": 32}, "team": {"name": "jroja", "id": 51}, "type": "correct", "challenge_id": 32, "id": 3838, "date": "2025-09-21T18:16:57.460981+00:00", "user": {"name": "sriram", "id": 92}}, {"challenge": {"name": "Schengen Shuffle I", "value": 225, "category": "OSINT", "id": 17}, "team": {"name": "jroja", "id": 51}, "type": "correct", "challenge_id": 17, "id": 3503, "date": "2025-09-21T18:08:20.450894+00:00", "user": {"name": "rojas80", "id": 80}}, {"challenge": {"name": "grep -R /cif fallctf", "value": 342, "category": "OSINT", "id": 66}, "team": {"name": "jroja", "id": 51}, "type": "correct", "challenge_id": 66, "id": 3381, "date": "2025-09-21T18:06:07.466168+00:00", "user": {"name": "sriram", "id": 92}}, {"challenge": {"name": "Champaign Problems 3", "value": 191, "category": "OSINT", "id": 61}, "team": {"name": "jroja", "id": 51}, "type": "correct", "challenge_id": 61, "id": 3185, "date": "2025-09-21T18:02:41.656340+00:00", "user": {"name": "rojas80", "id": 80}}, {"challenge": {"name": "Inspect Away 1", "value": 100, "category": "Web", "id": 18}, "team": {"name": "jroja", "id": 51}, "type": "correct", "challenge_id": 18, "id": 1902, "date": "2025-09-21T17:37:08.842042+00:00", "user": {"name": "rojas80", "id": 80}}, {"challenge": {"name": "I'm Blue 3", "value": 162, "category": "OSINT", "id": 57}, "team": {"name": "jroja", "id": 51}, "type": "correct", "challenge_id": 57, "id": 1738, "date": "2025-09-21T17:32:50.967163+00:00", "user": {"name": "sriram", "id": 92}}, {"challenge": {"name": "Inspect Away 7", "value": 218, "category": "Web", "id": 22}, "team": {"name": "jroja", "id": 51}, "type": "correct", "challenge_id": 22, "id": 1598, "date": "2025-09-21T17:30:21.030833+00:00", "user": {"name": "rojas80", "id": 80}}, {"challenge": {"name": "I'm Blue 2", "value": 147, "category": "OSINT", "id": 58}, "team": {"name": "jroja", "id": 51}, "type": "correct", "challenge_id": 58, "id": 1591, "date": "2025-09-21T17:30:14.456418+00:00", "user": {"name": "sriram", "id": 92}}, {"challenge": {"name": "FTX Feedback 1", "value": 269, "category": "Web", "id": 52}, "team": {"name": "jroja", "id": 51}, "type": "correct", "challenge_id": 52, "id": 1388, "date": "2025-09-21T17:26:21.468531+00:00", "user": {"name": "rojas80", "id": 80}}, {"challenge": {"name": "Champaign Problems 2", "value": 139, "category": "OSINT", "id": 64}, "team": {"name": "jroja", "id": 51}, "type": "correct", "challenge_id": 64, "id": 1119, "date": "2025-09-21T17:21:14.124663+00:00", "user": {"name": "sriram", "id": 92}}, {"challenge": {"name": "Champaign Problems 1", "value": 100, "category": "OSINT", "id": 60}, "team": {"name": "jroja", "id": 51}, "type": "correct", "challenge_id": 60, "id": 1108, "date": "2025-09-21T17:21:00.942068+00:00", "user": {"name": "sriram", "id": 92}}, {"challenge": {"name": "Inspect Away 3", "value": 100, "category": "Web", "id": 21}, "team": {"name": "jroja", "id": 51}, "type": "correct", "challenge_id": 21, "id": 668, "date": "2025-09-21T17:14:36.061351+00:00", "user": {"name": "rojas80", "id": 80}}, {"challenge": {"name": "Inspect Away 4", "value": 100, "category": "Web", "id": 20}, "team": {"name": "jroja", "id": 51}, "type": "correct", "challenge_id": 20, "id": 602, "date": "2025-09-21T17:13:26.857668+00:00", "user": {"name": "rojas80", "id": 80}}, {"challenge": {"name": "Inspect Away 2", "value": 100, "category": "Web", "id": 27}, "team": {"name": "jroja", "id": 51}, "type": "correct", "challenge_id": 27, "id": 566, "date": "2025-09-21T17:12:46.317807+00:00", "user": {"name": "rojas80", "id": 80}}, {"challenge": {"name": "Resume Upload", "value": 250, "category": "Welcome", "id": 42}, "team": {"name": "jroja", "id": 51}, "type": "correct", "challenge_id": 42, "id": 319, "date": "2025-09-21T17:08:37.588396+00:00", "user": {"name": "sriram", "id": 92}}, {"challenge": {"name": "Ask For Help 1", "value": 250, "category": "Welcome", "id": 38}, "team": {"name": "jroja", "id": 51}, "type": "correct", "challenge_id": 38, "id": 240, "date": "2025-09-21T17:06:20.264227+00:00", "user": {"name": "rojas80", "id": 80}}, {"challenge": {"name": "Pwny Notes", "value": 200, "category": "Welcome", "id": 43}, "team": {"name": "jroja", "id": 51}, "type": "correct", "challenge_id": 43, "id": 171, "date": "2025-09-21T17:04:30.557506+00:00", "user": {"name": "sriram", "id": 92}}, {"challenge": {"name": "Welcome to Fall CTF", "value": 100, "category": "Welcome", "id": 45}, "team": {"name": "jroja", "id": 51}, "type": "correct", "challenge_id": 45, "id": 79, "date": "2025-09-21T17:02:44.849608+00:00", "user": {"name": "rojas80", "id": 80}}], "meta": {"count": 27}}
