{"success": true, "data": [{"name": "Hint 265", "category": "hints", "icon": null, "date": "2025-09-21T20:32:50.767409+00:00", "user_id": 123, "user": 123, "id": 3345, "value": 0, "team": 52, "description": "Hint for First Rule of Security", "team_id": 52}, {"name": "Hint 355", "category": "hints", "icon": null, "date": "2025-09-21T20:32:15.995267+00:00", "user_id": 123, "user": 123, "id": 3341, "value": 0, "team": 52, "description": "Hint for Beyboard", "team_id": 52}, {"name": "Hint 354", "category": "hints", "icon": null, "date": "2025-09-21T20:32:09.765045+00:00", "user_id": 123, "user": 123, "id": 3337, "value": 0, "team": 52, "description": "Hint for Beyboard", "team_id": 52}, {"name": "Hint 261", "category": "hints", "icon": null, "date": "2025-09-21T20:08:33.158016+00:00", "user_id": 123, "user": 123, "id": 3100, "value": 0, "team": 52, "description": "Hint for SpecOps", "team_id": 52}, {"name": "Hint 260", "category": "hints", "icon": null, "date": "2025-09-21T20:08:27.774995+00:00", "user_id": 123, "user": 123, "id": 3098, "value": 0, "team": 52, "description": "Hint for SpecOps", "team_id": 52}, {"name": "Hint 263", "category": "hints", "icon": null, "date": "2025-09-21T20:07:17.323863+00:00", "user_id": 123, "user": 123, "id": 3093, "value": 0, "team": 52, "description": "Hint for String Theory", "team_id": 52}, {"name": "Hint 262", "category": "hints", "icon": null, "date": "2025-09-21T20:07:12.662941+00:00", "user_id": 123, "user": 123, "id": 3092, "value": 0, "team": 52, "description": "Hint for String Theory", "team_id": 52}, {"name": "Hint 342", "category": "hints", "icon": null, "date": "2025-09-21T19:51:45.280736+00:00", "user_id": 123, "user": 123, "id": 2899, "value": 0, "team": 52, "description": "Hint for Champaign Problems 4", "team_id": 52}, {"name": "Hint 273", "category": "hints", "icon": null, "date": "2025-09-21T19:08:05.709185+00:00", "user_id": 123, "user": 123, "id": 2326, "value": 0, "team": 52, "description": "Hint for grep -R /cif fallctf", "team_id": 52}, {"name": "Hint 326", "category": "hints", "icon": null, "date": "2025-09-21T19:04:09.169535+00:00", "user_id": 123, "user": 123, "id": 2258, "value": 0, "team": 52, "description": "Hint for Inspect Away 10", "team_id": 52}, {"name": "Hint 353", "category": "hints", "icon": null, "date": "2025-09-21T19:01:05.791305+00:00", "user_id": 123, "user": 123, "id": 2191, "value": 0, "team": 52, "description": "Hint for FTX Feedback 2", "team_id": 52}, {"name": "Hint 352", "category": "hints", "icon": null, "date": "2025-09-21T19:00:59.581368+00:00", "user_id": 123, "user": 123, "id": 2188, "value": 0, "team": 52, "description": "Hint for FTX Feedback 2", "team_id": 52}, {"name": "Hint 351", "category": "hints", "icon": null, "date": "2025-09-21T19:00:55.070586+00:00", "user_id": 123, "user": 123, "id": 2185, "value": 0, "team": 52, "description": "Hint for FTX Feedback 2", "team_id": 52}, {"name": "Hint 333", "category": "hints", "icon": null, "date": "2025-09-21T18:49:55.516679+00:00", "user_id": 123, "user": 123, "id": 1983, "value": 0, "team": 52, "description": "Hint for CS404 MP0", "team_id": 52}, {"name": "Hint 252", "category": "hints", "icon": null, "date": "2025-09-21T18:40:22.063041+00:00", "user_id": 123, "user": 123, "id": 1763, "value": 0, "team": 52, "description": "Hint for AES ECEB", "team_id": 52}, {"name": "Hint 313", "category": "hints", "icon": null, "date": "2025-09-21T18:38:36.219828+00:00", "user_id": 123, "user": 123, "id": 1723, "value": 0, "team": 52, "description": "Hint for Discord Suite 2", "team_id": 52}, {"name": "Hint 327", "category": "hints", "icon": null, "date": "2025-09-21T18:25:50.889567+00:00", "user_id": 123, "user": 123, "id": 1472, "value": 0, "team": 52, "description": "Hint for Inspect Away 6", "team_id": 52}, {"name": "Hint 255", "category": "hints", "icon": null, "date": "2025-09-21T18:00:04.848900+00:00", "user_id": 123, "user": 123, "id": 915, "value": 0, "team": 52, "description": "Hint for Find the Paper", "team_id": 52}, {"name": "Hint 254", "category": "hints", "icon": null, "date": "2025-09-21T17:09:30.736878+00:00", "user_id": 123, "user": 123, "id": 108, "value": 0, "team": 52, "description": "Hint for Call the eXORcist", "team_id": 52}, {"name": "Hint 253", "category": "hints", "icon": null, "date": "2025-09-21T17:09:24.968951+00:00", "user_id": 123, "user": 123, "id": 105, "value": 0, "team": 52, "description": "Hint for Call the eXORcist", "team_id": 52}], "meta": {"count": 20}}
